metrictable.py
metrictable-0.0.4.dist-info/LICENSE
metrictable-0.0.4.dist-info/METADATA
metrictable-0.0.4.dist-info/WHEEL
metrictable-0.0.4.dist-info/top_level.txt
metrictable-0.0.4.dist-info/RECORD
