Metadata-Version: 2.1
Name: metrictable
Version: 0.0.4
Summary: Description: metrics for regression and classification
Home-page: UNKNOWN
Author: sarath babu
Author-email: babusarath05@gmail.com
License: UNKNOWN
Keywords: python,regression,metrics,adj r2_score,r2_score,rmse
Platform: UNKNOWN
Classifier: Development Status :: 1 - Planning
Classifier: Intended Audience :: Developers
Classifier: Programming Language :: Python :: 3
Classifier: Operating System :: Unix
Classifier: Operating System :: MacOS :: MacOS X
Classifier: Operating System :: Microsoft :: Windows
Requires-Dist: sklearn
Requires-Dist: pandas
Requires-Dist: metrictable
